{
  "name": "Sideswap",
  "logoURI": "https://d.sideswap.finance/favicon.png",
  "keywords": [
    "sideswap",
    "defi"
  ],
  "timestamp": "2023-06-22T16:37:00.000+00:00",
  "tokens": [
    {
      "chainId": 12008,
      "address": "0xBB9f0A3A082Dde7B377c87a932bAFE2C6e78ae6B",
      "name": "WETH",
      "symbol": "WETH",
      "decimals": 18,
      "logoURI": "https://raw.githubusercontent.com/SideSwapIN/tokenlist/master/assets/weth.png"
    },
    {
      "chainId": 12008,
      "address": "0xeC0675462bc7cAb52cbc02cb97fF75714d5499F7",
      "name": "USDT",
      "symbol": "USDT",
      "decimals": 18,
      "logoURI": "https://raw.githubusercontent.com/SideSwapIN/tokenlist/master/assets/usdt.png"
    },
    {
      "chainId": 12008,
      "address": "0xD087bDEd6Dd18B5AB8812F4DA77e83e68754e960",
      "name": "USDC",
      "symbol": "USDC",
      "decimals": 18,
      "logoURI": "https://raw.githubusercontent.com/SideSwapIN/tokenlist/master/assets/usdc.png"
    },
    {
      "chainId": 51178,
      "address": "0x91753D74B3922B445f45a362e9B98e159A0340E1",
      "name": "WETH",
      "symbol": "WETH",
      "decimals": 18,
      "logoURI": "https://raw.githubusercontent.com/SideSwapIN/tokenlist/master/assets/weth.png"
    },
    {
      "chainId": 51178,
      "address": "0x80920B48664b45c8FD9C2f4201AcFf6249c72768",
      "name": "USDT",
      "symbol": "USDT",
      "decimals": 18,
      "logoURI": "https://raw.githubusercontent.com/SideSwapIN/tokenlist/master/assets/usdt.png"
    },
    {
      "chainId": 51178,
      "address": "0x78bE7ab62921ec295a400Ef7414F2a01fFD5476F",
      "name": "USDC",
      "symbol": "USDC",
      "decimals": 18,
      "logoURI": "https://raw.githubusercontent.com/SideSwapIN/tokenlist/master/assets/usdc.png"
    }
  ],
  "version": {
    "major": 1,
    "minor": 0,
    "patch": 0
  }
}